odoo/addons/account_fiscal_year/README.rst
odoo/addons/account_fiscal_year/__init__.py
odoo/addons/account_fiscal_year/__manifest__.py
odoo/addons/account_fiscal_year/data/date_range_type.xml
odoo/addons/account_fiscal_year/i18n/account_fiscal_year.pot
odoo/addons/account_fiscal_year/i18n/fr.po
odoo/addons/account_fiscal_year/i18n/fr_FR.po
odoo/addons/account_fiscal_year/i18n/it.po
odoo/addons/account_fiscal_year/i18n/nl.po
odoo/addons/account_fiscal_year/models/__init__.py
odoo/addons/account_fiscal_year/models/account_fiscal_year.py
odoo/addons/account_fiscal_year/models/res_company.py
odoo/addons/account_fiscal_year/readme/CONTRIBUTORS.rst
odoo/addons/account_fiscal_year/readme/DESCRIPTION.rst
odoo/addons/account_fiscal_year/readme/ROADMAP.rst
odoo/addons/account_fiscal_year/security/account_fiscal_year_rule.xml
odoo/addons/account_fiscal_year/security/ir.model.access.csv
odoo/addons/account_fiscal_year/static/description/icon.png
odoo/addons/account_fiscal_year/static/description/index.html
odoo/addons/account_fiscal_year/tests/__init__.py
odoo/addons/account_fiscal_year/tests/test_account_fiscal_year.py
odoo/addons/account_fiscal_year/views/account_fiscal_year_views.xml
odoo14_addon_account_fiscal_year-14.0.1.2.1.dist-info/METADATA
odoo14_addon_account_fiscal_year-14.0.1.2.1.dist-info/WHEEL
odoo14_addon_account_fiscal_year-14.0.1.2.1.dist-info/top_level.txt
odoo14_addon_account_fiscal_year-14.0.1.2.1.dist-info/RECORD
