Metadata-Version: 2.1
Name: odoo14-addon-account-fiscal-year
Version: 14.0.1.2.1
Summary: Create Account Fiscal Year
Home-page: https://github.com/OCA/account-financial-tools
Author: Agile Business Group, Camptocamp SA, Odoo Community Association (OCA)
Author-email: support@odoo-community.org
License: AGPL-3
Platform: UNKNOWN
Classifier: Programming Language :: Python
Classifier: Framework :: Odoo
Classifier: Framework :: Odoo :: 14.0
Classifier: License :: OSI Approved :: GNU Affero General Public License v3
Classifier: Development Status :: 5 - Production/Stable
Requires-Python: >=3.6
Requires-Dist: odoo14-addon-date-range
Requires-Dist: odoo (<14.1dev,>=14.0a)
